MANIFEST.in
README.md
setup.py
django_dslforms.egg-info/PKG-INFO
django_dslforms.egg-info/SOURCES.txt
django_dslforms.egg-info/dependency_links.txt
django_dslforms.egg-info/not-zip-safe
django_dslforms.egg-info/requires.txt
django_dslforms.egg-info/top_level.txt
dslforms/__init__.py
dslforms/forms.py
dslforms/models.py
dslforms/parser.py
dslforms/test_urls.py
dslforms/tests.py
dslforms/util.py
dslforms/views.py