Metadata-Version: 1.0
Name: django-dslforms
Version: 1.1.1
Summary: Create simple Django forms with a mini-language in your templates.
Home-page: https://github.com/prestontimmons/django-dslforms
Author: Preston Timmons
Author-email: prestontimmons@gmail.com
License: UNKNOWN
Platform: UNKNOWN
